whetstone/__init__.py
whetstone/test.py
whetstone/metrics/text/__init__.py
whetstone/metrics/text/readability_metrics.py
whetstone/utils/__init__.py
whetstone/utils/text/__init__.py
whetstone/utils/text/text_parsers.py
whetstone_ml-0.1.0.dev19.dist-info/LICENSE
whetstone_ml-0.1.0.dev19.dist-info/METADATA
whetstone_ml-0.1.0.dev19.dist-info/WHEEL
whetstone_ml-0.1.0.dev19.dist-info/top_level.txt
whetstone_ml-0.1.0.dev19.dist-info/RECORD
