Metadata-Version: 2.1
Name: whetstone-ml
Version: 0.1.0.dev19
Summary: This package supports a variety of machine learning validation and evaluation tasks.
Author-email: David Hundley <david.k.hundley@gmail.com>
License:                                  Apache License
Project-URL: Homepage, https://github.com/dkhundley/whetstone-ml
Project-URL: Documentation, https://github.com/dkhundley/whetstone-ml
Requires-Python: >=3.10
License-File: LICENSE
